wavecell/__init__.py
wavecell/wavecell.py
wavecell_py-0.0.4.dist-info/LICENSE.txt
wavecell_py-0.0.4.dist-info/METADATA
wavecell_py-0.0.4.dist-info/WHEEL
wavecell_py-0.0.4.dist-info/top_level.txt
wavecell_py-0.0.4.dist-info/RECORD
